deadsimplekv/__init__.py
deadsimplekv-0.3.2.dist-info/LICENSE
deadsimplekv-0.3.2.dist-info/METADATA
deadsimplekv-0.3.2.dist-info/WHEEL
deadsimplekv-0.3.2.dist-info/top_level.txt
deadsimplekv-0.3.2.dist-info/RECORD
